{"s_1": {"t_1_1": ["Apart", "apart", "r", "00180756-r"], "t_1_4": ["honeybee", "honeybee", "n", "02208280-n"], "t_1_6": ["practically", "practically", "r", "00053744-r"], "t_1_8": ["bees", "bee", "n", "02206856-n"], "t_1_10": ["bumblebees", "bumblebee", "n", "02209624-n"], "t_1_11": ["hibernate", "hibernate", "v", "00015946-v"], "t_1_14": ["state", "state", "n", "00024720-n"], "t_1_16": ["torpor", "torpor", "n", "14014621-n"]}, "s_2": {"t_2_1": ["Occasionally", "occasionally", "r", "00021212-r"], "t_2_5": ["come_across", "come_across", "v", "02286687-v"], "t_2_6": ["one", "one", "a", "02186338-s"], "t_2_8": ["two", "two", "a", "02186470-s"], "t_2_9": ["bumblebees", "bumblebee", "n", "02209624-n"], "t_2_12": ["cold", "cold", "a", "01251128-a"], "t_2_13": ["season", "season", "n", "15236475-n"], "t_2_18": ["turning_over", "turn_over", "v", "01309701-v"], "t_2_19": ["sods", "sod", "n", "09463919-n"], "t_2_22": ["garden", "garden", "n", "03417345-n"], "t_2_27": ["be", "be", "v", "02604760-v"], "t_2_29": ["really", "really", "r", "00037226-r"], "t_2_30": ["keen", "keen", "a", "01744515-s"], "t_2_31": ["observer", "observer", "n", "09626589-n"], "t_2_33": ["see", "see", "v", "02129289-v"], "t_2_35": ["at_all", "at_all", "r", "00056729-r"]}, "s_3": {"t_3_2": ["keep", "keep", "v", "02681795-v"], "t_3_4": ["wings", "wing", "n", "02151625-n"], "t_3_6": ["feet", "foot", "n", "02322213-n"], "t_3_7": ["pressed", "press", "v", "01447257-v"], "t_3_8": ["tightly", "tightly", "r", "00300137-r"], "t_3_11": ["bodies", "body", "n", "05216365-n"], "t_3_16": ["often", "often", "r", "00035058-r"], "t_3_17": ["colorful", "colorful", "a", "00402419-a"], "t_3_18": ["attire", "attire", "n", "02756098-n"], "t_3_21": ["very", "very", "r", "00031899-r"], "t_3_22": ["well", "well", "r", "00012531-r"], "t_3_23": ["mistake", "mistake", "n", "00070965-n"], "t_3_26": ["lumps", "lump", "n", "07961016-n"], "t_3_28": ["dirt", "dirt", "n", "14844693-n"]}, "s_4": {"t_4_3": ["add", "add", "v", "01027174-v"], "t_4_4": ["at_once", "at_once", "r", "00048739-r"], "t_4_7": ["animals", "animal", "n", "00015388-n"], "t_4_8": ["are", "be", "v", "02616386-v"], "t_4_11": ["call", "call", "v", "01028748-v"], "t_4_13": ["queens", "queen", "n", "02313008-n"], "t_4_16": ["young", "young", "a", "01646941-a"], "t_4_17": ["females", "female", "n", "01320872-n"], "t_4_20": ["mated", "mate", "v", "01428853-v"], "t_4_23": ["previous", "previous", "a", "00127137-s"], "t_4_24": ["summer", "summer", "n", "15237250-n"], "t_4_26": ["autumn", "autumn", "n", "15236859-n"]}, "s_5": {"t_5_2": ["is", "be", "v", "02604760-v"], "t_5_5": ["alone", "alone", "r", "00008600-r"], "t_5_8": ["future", "future", "n", "15121625-n"], "t_5_11": ["race", "race", "n", "08110648-n"], "t_5_12": ["depends", "depend_on", "v", "02711987-v"], "t_5_17": ["relatives", "relative", "n", "01328302-n"], "t_5_19": ["mothers", "mother", "n", "10332385-n"], "t_5_21": ["husbands", "husband", "n", "10193967-n"], "t_5_23": ["brothers", "brother", "n", "09876454-n"], "t_5_26": ["unmated", "unmated", "a", "01483143-a"], "t_5_27": ["sisters", "sister", "n", "10602985-n"], "t_5_30": ["perished", "perish", "v", "00358431-v"], "t_5_33": ["arrival", "arrival", "n", "00048225-n"], "t_5_36": ["cold_weather", "cold_weather", "n", "11440012-n"]}, "s_6": {"t_6_1": ["Even", "even", "r", "00017445-r"], "t_6_2": ["some", "some", "a", "02267308-a"], "t_6_5": ["queens", "queen", "n", "02313008-n"], "t_6_7": ["die", "die", "v", "00358431-v"], "t_6_8": ["before", "before", "r", "00060939-r"], "t_6_10": ["winter", "winter", "n", "15237782-n"], "t_6_11": ["is", "be", "v", "02604760-v"], "t_6_12": ["over", "over", "a", "01003277-s"], "t_6_14": ["falling", "fall", "v", "00147815-v"], "t_6_15": ["prey", "prey", "n", "10470460-n"], "t_6_17": ["enemies", "enemy", "n", "10055847-n"], "t_6_19": ["disease", "disease", "n", "14070360-n"]}, "s_7": {"t_7_2": ["survivors", "survivor", "n", "01324142-n"], "t_7_3": ["emerge", "emerge", "v", "00423971-v"], "t_7_6": ["nice", "nice", "a", "01586342-a"], "t_7_8": ["sunny", "sunny", "a", "00363938-s"], "t_7_9": ["day", "day", "n", "15157225-n"], "t_7_11": ["March", "march", "n", "15210870-n"], "t_7_13": ["April", "april", "n", "15211189-n"], "t_7_17": ["temperature", "temperature", "n", "05011790-n"], "t_7_18": ["is", "be", "v", "02604760-v"], "t_7_19": ["close", "close", "a", "00444519-a"], "t_7_21": ["50", "50", "a", "02191232-s"], "t_7_23": ["F", "f", "n", "13714641-n"], "t_7_26": ["is", "be", "v", "02749904-v"], "t_7_27": ["not", "not", "r", "00024073-r"], "t_7_28": ["too_much", "too_much", "r", "00415963-r"], "t_7_29": ["wind", "wind", "n", "11525955-n"]}, "s_8": {"t_8_1": ["Now", "now", "n", "15119919-n"], "t_8_3": ["thing", "thing", "n", "00034479-n"], "t_8_7": ["do", "do", "v", "02560585-v"], "t_8_8": ["is", "be", "v", "02616386-v"], "t_8_10": ["find", "find", "v", "02213336-v"], "t_8_12": ["a_couple_of", "a_couple_of", "a", "01553340-s"], "t_8_14": ["wonderful", "wonderful", "a", "01676517-s"], "t_8_15": ["flowering", "flowering", "n", "13439570-n"], "t_8_16": ["currants", "currant", "n", "07744246-n"], "t_8_19": ["red", "red", "a", "00381097-s"], "t_8_20": ["Ribes_sanguineum", "ribes_sanguineum", "n", "12805899-n"], "t_8_23": ["Pacific_Northwest", "location", "n", "00027167-n"], "t_8_26": ["otherwise", "otherwise", "r", "00113082-r"], "t_8_28": ["good", "good", "a", "01123148-a"], "t_8_29": ["sloe", "sloe", "n", "12638753-n"], "t_8_30": ["tree", "tree", "n", "13104059-n"], "t_8_33": ["perhaps", "perhaps", "r", "00300247-r"], "t_8_35": ["nice", "nice", "a", "01586342-a"], "t_8_36": ["pussy_willow", "pussy_willow", "n", "12727101-n"], "t_8_38": ["bloom", "bloom", "v", "00294245-v"], "t_8_40": ["preferably", "preferably", "r", "00115554-r"], "t_8_43": ["male", "male", "a", "01476685-a"], "t_8_45": ["staminate", "staminate", "a", "01477251-s"], "t_8_46": ["catkins", "catkin", "n", "11674798-n"]}, "s_9": {"t_9_2": ["blooms", "bloom", "n", "11669335-n"], "t_9_4": ["Ribes", "ribes", "n", "12804866-n"], "t_9_8": ["willow", "willow", "n", "12724942-n"], "t_9_10": ["sloe", "sloe", "n", "12638753-n"], "t_9_11": ["are", "be", "v", "02616386-v"], "t_9_13": ["places", "place", "n", "08664443-n"], "t_9_15": ["large_numbers", "large_number", "n", "13775093-n"], "t_9_18": ["early", "early", "a", "01648617-s"], "t_9_19": ["insects", "insect", "n", "02159955-n"], "t_9_21": ["assemble", "assemble", "v", "02428924-v"], "t_9_23": ["honeybees", "honeybee", "n", "02208280-n"], "t_9_25": ["bumblebees", "bumblebee", "n", "02209624-n"], "t_9_28": ["other", "other", "a", "02069355-a"], "t_9_29": ["wild", "wild", "a", "02389220-a"], "t_9_30": ["bees", "bee", "n", "02206856-n"], "t_9_33": ["also", "also", "r", "00047534-r"], "t_9_34": ["various", "various", "a", "02065665-s"], "t_9_35": ["kinds", "kind", "n", "05839024-n"], "t_9_37": ["flies", "fly", "n", "02190166-n"]}, "s_10": {"t_10_2": ["is", "be", "v", "02604760-v"], "t_10_4": ["happy", "happy", "a", "01148283-a"], "t_10_6": ["buzzing", "buzzing", "a", "01920697-s"], "t_10_7": ["crowd", "crowd", "n", "08182379-n"]}, "s_11": {"t_11_2": ["male", "male", "a", "01476685-a"], "t_11_3": ["willow", "willow", "n", "12724942-n"], "t_11_4": ["catkin", "catkin", "n", "11674798-n"], "t_11_5": ["is", "be", "v", "02604760-v"], "t_11_6": ["composed", "composed", "v", "02621244-v"], "t_11_9": ["large_number", "large_number", "n", "13775093-n"], "t_11_11": ["small", "small", "a", "01391351-a"], "t_11_12": ["flowers", "flower", "n", "11669921-n"]}, "s_12": {"t_12_2": ["is", "be", "v", "02604760-v"], "t_12_3": ["not", "not", "r", "00024073-r"], "t_12_4": ["difficult", "difficult", "a", "00744916-a"], "t_12_6": ["see", "see", "v", "02129289-v"], "t_12_9": ["stamens", "stamen", "n", "11675096-n"], "t_12_12": ["catkin", "catkin", "n", "11674798-n"], "t_12_14": ["always", "always", "r", "00019339-r"], "t_12_15": ["arranged", "arrange", "v", "01463963-v"], "t_12_17": ["pairs", "pair", "n", "07976936-n"], "t_12_21": ["each", "each", "a", "02269635-s"], "t_12_22": ["individual", "individual", "a", "00493460-a"], "t_12_23": ["flower", "flower", "n", "11669921-n"], "t_12_24": ["is", "be", "v", "02616386-v"], "t_12_25": ["nothing", "nothing", "n", "13740168-n"], "t_12_27": ["one", "one", "n", "13742573-n"], "t_12_28": ["such", "such", "a", "01554230-s"], "t_12_29": ["pair", "pair", "n", "07985223-n"], "t_12_30": ["standing", "stand", "v", "01546111-v"], "t_12_33": ["green", "green", "a", "00375969-s"], "t_12_35": ["black", "black", "a", "00392812-a"], "t_12_36": ["tipped", "tip", "v", "00511178-v"], "t_12_37": ["little", "little", "a", "01391351-a"], "t_12_38": ["scale", "scale", "n", "13155759-n"]}, "s_13": {"t_13_2": ["scrutinizing", "scrutinize", "v", "02153387-v"], "t_13_4": ["flowers", "flower", "n", "11669921-n"], "t_13_8": ["also", "also", "r", "00047534-r"], "t_13_9": ["notice", "notice", "v", "02154508-v"], "t_13_12": ["scale", "scale", "n", "13155759-n"], "t_13_13": ["bears", "bear", "v", "02700867-v"], "t_13_14": ["one", "one", "a", "02186338-s"], "t_13_16": ["two", "two", "a", "02186470-s"], "t_13_17": ["tiny", "tiny", "a", "01392249-s"], "t_13_18": ["warts", "wart", "n", "13895852-n"]}, "s_14": {"t_14_2": ["are", "be", "v", "02616386-v"], "t_14_4": ["nectaries", "nectary", "n", "11683838-n"], "t_14_6": ["honey", "honey", "n", "07858978-n"], "t_14_7": ["glands", "gland", "n", "05327767-n"], "t_14_9": ["Fig.", "fig", "n", "06999647-n"], "t_14_10": ["26", "26", "a", "02188913-s"], "t_14_12": ["page", "page", "n", "06256697-n"]}, "s_15": {"t_15_2": ["staminate", "staminate", "a", "01477251-s"], "t_15_3": ["willow", "willow", "n", "12724942-n"], "t_15_4": ["catkins", "catkin", "n", "11674798-n"], "t_15_6": ["then", "then", "r", "00118032-r"], "t_15_8": ["provide", "provide", "v", "02327200-v"], "t_15_10": ["visitors", "visitor", "n", "10757193-n"], "t_15_13": ["nectar", "nectar", "n", "14846779-n"], "t_15_15": ["pollen", "pollen", "n", "11675537-n"], "t_15_18": ["marvelous", "marvelous", "a", "00646117-s"], "t_15_19": ["arrangement", "arrangement", "n", "05795044-n"], "t_15_23": ["provides", "provide", "v", "02327200-v"], "t_15_24": ["exactly", "exactly", "r", "00158309-r"], "t_15_27": ["bee", "bee", "n", "02206856-n"], "t_15_28": ["queens", "queen", "n", "02313008-n"], "t_15_31": ["make", "make", "v", "01653873-v"], "t_15_33": ["beebread", "beebread", "n", "14774090-n"], "t_15_36": ["combination", "combination", "n", "07963711-n"], "t_15_38": ["honey", "honey", "n", "07858978-n"], "t_15_40": ["pollen", "pollen", "n", "11675537-n"], "t_15_44": ["young", "young", "n", "01321579-n"], "t_15_47": ["species", "species", "n", "08110373-n"], "t_15_49": ["fed", "feed", "v", "01182021-v"]}, "s_16": {"t_16_2": ["only", "only", "a", "02214736-s"], "t_16_3": ["exception", "exception", "n", "05707269-n"], "t_16_6": ["is", "be", "v", "02616386-v"], "t_16_7": ["certain", "certain", "a", "00700884-s"], "t_16_8": ["bees", "bee", "n", "02206856-n"], "t_16_11": ["become", "become", "v", "02626604-v"], "t_16_12": ["parasites", "parasite", "n", "01384687-n"]}, "s_17": {"t_17_3": ["deal", "deal", "v", "02370987-v"], "t_17_6": ["later_on", "later_on", "r", "00061203-r"]}, "s_18": {"t_18_1": ["Quite", "quite", "r", "00018577-r"], "t_18_2": ["often", "often", "r", "00035058-r"], "t_18_4": ["honeybees", "honeybee", "n", "02208280-n"], "t_18_5": ["form", "form", "v", "02621395-v"], "t_18_7": ["majority", "majority", "n", "05122557-n"], "t_18_10": ["willow", "willow", "n", "12724942-n"], "t_18_11": ["catkins", "catkin", "n", "11674798-n"]}, "s_19": {"t_19_4": ["already", "already", "r", "00031798-r"], "t_19_5": ["seen", "see", "v", "00920336-v"], "t_19_8": ["first", "first", "a", "02202047-s"], "t_19_9": ["chapter", "chapter", "n", "06396142-n"], "t_19_11": ["bumblebees", "bumblebee", "n", "02209624-n"], "t_19_12": ["are", "be", "v", "02604760-v"], "t_19_13": ["bigger", "big", "a", "01382086-a"], "t_19_15": ["hairier", "hairy", "a", "00212173-a"], "t_19_18": ["much", "much", "r", "00059086-r"], "t_19_19": ["more", "more", "r", "00099341-r"], "t_19_20": ["colorful", "colorful", "a", "00402419-a"], "t_19_22": ["honeybees", "honeybee", "n", "02208280-n"], "t_19_24": ["exhibiting", "exhibit", "v", "02631856-v"], "t_19_25": ["various", "various", "a", "02065665-s"], "t_19_26": ["combinations", "combination", "n", "07963711-n"], "t_19_28": ["black", "black", "n", "04960277-n"], "t_19_30": ["yellow", "yellow", "n", "04965661-n"], "t_19_32": ["white", "white", "n", "04960729-n"], "t_19_34": ["orange", "orange", "n", "04965179-n"]}, "s_20": {"t_20_1": ["Let", "let", "v", "02423183-v"], "t_20_3": ["not", "not", "r", "00024073-r"], "t_20_4": ["try", "try", "v", "02530167-v"], "t_20_6": ["key", "key", "v", "00652346-v"], "t_20_11": ["stage", "stage", "n", "15290337-n"], "t_20_14": ["game", "game", "n", "00430606-n"], "t_20_17": ["let", "let", "v", "02423183-v"], "t_20_19": ["just", "just", "r", "00004722-r"], "t_20_20": ["call", "call", "v", "01028748-v"], "t_20_22": ["Bombus", "bombus", "n", "02209508-n"], "t_20_26": ["be", "be", "v", "02603699-v"], "t_20_27": ["several", "several", "a", "02268268-s"], "t_20_28": ["dozen", "dozen", "n", "13746785-n"], "t_20_29": ["species", "species", "n", "08110373-n"], "t_20_32": ["United_States", "united_states", "n", "09044862-n"], "t_20_33": ["alone", "alone", "r", "00008600-r"]}, "s_21": {"t_21_3": ["really", "really", "r", "00037226-r"], "t_21_4": ["insist", "insist", "v", "00818974-v"], "t_21_6": ["knowing", "know", "v", "00594621-v"], "t_21_8": ["names", "name", "n", "06333653-n"], "t_21_11": ["excellent", "excellent", "a", "02343110-s"], "t_21_12": ["book", "book", "n", "06410904-n"], "t_21_16": ["species", "species", "n", "08110373-n"], "t_21_17": ["is", "be", "v", "02616386-v"], "t_21_18": ["Bumblebees", "bumblebee", "n", "02209624-n"], "t_21_21": ["Ways", "way", "n", "00415676-n"], "t_21_23": ["O._E._Plath", "person", "n", "00007846-n"]}, "s_22": {"t_22_3": ["manage", "manage", "v", "02522864-v"], "t_22_5": ["keep", "keep", "v", "00732552-v"], "t_22_6": ["track", "track", "n", "05826914-n"], "t_22_9": ["Bombus", "bombus", "n", "02209508-n"], "t_22_10": ["queen", "queen", "n", "02313008-n"], "t_22_14": ["left", "leave", "v", "02009433-v"], "t_22_16": ["feeding", "feeding", "n", "00838367-n"], "t_22_17": ["place", "place", "n", "08664443-n"], "t_22_21": ["discover", "discover", "v", "01637982-v"], "t_22_23": ["snug", "snug", "a", "01885991-s"], "t_22_24": ["little", "little", "a", "01391351-a"], "t_22_25": ["hideout", "hideout", "n", "08584218-n"], "t_22_29": ["fixed_up", "fix_up", "v", "01203369-v"], "t_22_34": ["woke_up", "wake_up", "v", "00018813-v"], "t_22_37": ["winter", "winter", "n", "15237782-n"], "t_22_38": ["sleep", "sleep", "n", "14024882-n"]}, "s_23": {"t_23_2": ["befits", "befit", "v", "02699941-v"], "t_23_4": ["queen", "queen", "n", "02313008-n"], "t_23_7": ["bumblebee", "bumblebee", "n", "02209624-n"], "t_23_8": ["female", "female", "n", "01320872-n"], "t_23_9": ["is", "be", "v", "02604760-v"], "t_23_10": ["rather", "rather", "r", "00018302-r"], "t_23_11": ["choosy", "choosy", "a", "00984251-s"], "t_23_14": ["spend", "spend", "v", "02708420-v"], "t_23_15": ["considerable", "considerable", "a", "00624026-a"], "t_23_16": ["time", "time", "n", "15270431-n"], "t_23_17": ["searching", "search", "v", "01315613-v"], "t_23_20": ["suitable", "suitable", "a", "01020885-s"], "t_23_21": ["nesting_place", "nesting_place", "n", "08610975-n"]}, "s_24": {"t_24_1": ["Most", "most", "a", "01555732-a"], "t_24_2": ["species", "species", "n", "08110373-n"], "t_24_3": ["seem", "seem", "v", "02133435-v"], "t_24_5": ["prefer", "prefer", "v", "00679389-v"], "t_24_7": ["ready-made", "ready-made", "a", "00672621-a"], "t_24_8": ["hollow", "hollow", "n", "09304750-n"], "t_24_11": ["deserted", "deserted", "v", "00614057-v"], "t_24_12": ["mouse_nest", "mouse_nest", "n", "09362207-n"], "t_24_15": ["bird_house", "birdhouse", "n", "02843684-n"], "t_24_19": ["hole", "hole", "n", "09304465-n"], "t_24_20": ["made", "make", "v", "01617192-v"], "t_24_23": ["woodpecker", "woodpecker", "n", "01838598-n"], "t_24_25": ["some", "some", "a", "02267308-a"], "t_24_26": ["show", "show", "v", "02148788-v"], "t_24_28": ["definite", "definite", "a", "00700451-a"], "t_24_29": ["liking", "liking", "n", "07497473-n"], "t_24_31": ["making", "make", "v", "01654628-v"], "t_24_33": ["nest", "nest", "n", "09369169-n"], "t_24_35": ["moss", "moss", "n", "11537506-n"]}, "s_25": {"t_25_1": ["Once", "once", "r", "00181342-r"], "t_25_4": ["made_up_her_mind", "make_up_one's_mind", "v", "00697589-v"], "t_25_7": ["queen", "queen", "n", "02313008-n"], "t_25_8": ["starts_out", "start_out", "v", "02014165-v"], "t_25_10": ["constructing", "construct", "v", "01654628-v"], "t_25_14": ["chosen", "chosen", "n", "09921034-n"], "t_25_15": ["abode", "abode", "n", "03259505-n"], "t_25_18": ["small", "small", "a", "01391351-a"], "t_25_20": ["floor", "floor", "n", "03365592-n"], "t_25_23": ["dried", "dried", "a", "02553017-s"], "t_25_24": ["grass", "grass", "n", "12102133-n"], "t_25_27": ["woolly", "woolly", "a", "01154351-s"], "t_25_28": ["material", "material", "n", "14580897-n"]}, "s_26": {"t_26_5": ["builds", "build", "v", "01654628-v"], "t_26_8": ["egg", "egg", "n", "01460457-n"], "t_26_9": ["compartment", "compartment", "n", "03080309-n"], "t_26_13": ["egg", "egg", "n", "01460457-n"], "t_26_14": ["cell", "cell", "n", "02991711-n"], "t_26_18": ["filled", "filled", "a", "01084644-s"], "t_26_21": ["famous", "famous", "a", "01375831-s"], "t_26_22": ["pollen", "pollen", "n", "11675537-n"], "t_26_24": ["nectar", "nectar", "n", "14846779-n"], "t_26_25": ["mixture", "mixture", "n", "07882497-n"], "t_26_26": ["called", "called", "v", "01028748-v"], "t_26_27": ["beebread", "beebread", "n", "14774090-n"]}, "s_27": {"t_27_2": ["also", "also", "r", "00047534-r"], "t_27_3": ["builds", "build", "v", "01654628-v"], "t_27_4": ["one", "one", "a", "02186338-s"], "t_27_6": ["two", "two", "a", "02186470-s"], "t_27_7": ["waxen", "waxen", "a", "03004852-a"], "t_27_8": ["cups", "cup", "n", "13904665-n"], "t_27_11": ["fills", "fill", "v", "00452512-v"], "t_27_13": ["honey", "honey", "n", "07858978-n"]}, "s_28": {"t_28_1": ["Then", "then", "r", "00117620-r"], "t_28_4": ["group", "group", "n", "00031264-n"], "t_28_6": ["eggs", "egg", "n", "01460457-n"], "t_28_8": ["deposited", "deposit", "v", "01575675-v"], "t_28_11": ["cavity", "cavity", "n", "09393108-n"], "t_28_14": ["beebread", "beebread", "n", "14774090-n"], "t_28_15": ["loaf", "loaf", "n", "07683786-n"], "t_28_18": ["egg", "egg", "n", "01460457-n"], "t_28_19": ["compartment", "compartment", "n", "03080309-n"], "t_28_21": ["closed", "close", "v", "01345109-v"]}, "s_29": {"t_29_2": ["queen", "queen", "n", "02313008-n"], "t_29_3": ["afterward", "afterward", "r", "00061203-r"], "t_29_4": ["keeps", "keep", "v", "02684924-v"], "t_29_5": ["incubating", "incubate", "v", "00060185-v"], "t_29_7": ["guarding", "guard", "v", "02456031-v"], "t_29_9": ["eggs", "egg", "n", "01460457-n"], "t_29_12": ["mother", "mother", "n", "10332385-n"], "t_29_13": ["hen", "hen", "n", "01792640-n"], "t_29_15": ["taking", "take", "v", "01156834-v"], "t_29_17": ["sip", "sip", "n", "00843494-n"], "t_29_18": ["from_time_to_time", "from_time_to_time", "r", "00021212-r"], "t_29_21": ["rather", "rather", "r", "00018302-r"], "t_29_22": ["liquid", "liquid", "a", "02261386-a"], "t_29_23": ["honey", "honey", "n", "07858978-n"], "t_29_26": ["honey", "honey", "n", "07858978-n"], "t_29_27": ["pots", "pot", "n", "13769033-n"]}, "s_30": {"t_30_3": ["larvae", "larva", "n", "02311060-n"], "t_30_4": ["hatch", "hatch", "v", "00063095-v"], "t_30_7": ["feed_on", "feed_on", "v", "01203234-v"], "t_30_9": ["beebread", "beebread", "n", "14774090-n"], "t_30_13": ["also", "also", "r", "00047534-r"], "t_30_14": ["receive", "receive", "v", "02210119-v"], "t_30_15": ["extra", "extra", "n", "10676569-n"], "t_30_16": ["honey", "honey", "n", "07858978-n"], "t_30_17": ["meals", "meal", "n", "07573696-n"], "t_30_20": ["mother", "mother", "n", "10332385-n"]}, "s_31": {"t_31_2": ["continues", "continue", "v", "02684924-v"], "t_31_4": ["add", "add", "v", "00182406-v"], "t_31_7": ["pollen", "pollen", "n", "11675537-n"], "t_31_8": ["supply", "supply", "n", "13777344-n"], "t_31_9": ["as_needed", "as_needed", "r", "00181418-r"]}, "s_32": {"t_32_2": ["larvae", "larva", "n", "02311060-n"], "t_32_4": ["kept", "keep", "v", "02681795-v"], "t_32_5": ["warm", "warm", "a", "02529264-a"], "t_32_8": ["queen", "queen", "n", "02313008-n"], "t_32_10": ["are", "be", "v", "02604760-v"], "t_32_11": ["full_grown", "full-grown", "a", "01488616-s"], "t_32_14": ["ten", "ten", "a", "02187296-s"], "t_32_15": ["days", "day", "n", "15155220-n"]}, "s_33": {"t_33_2": ["now", "now", "r", "00049433-r"], "t_33_3": ["makes", "make", "v", "01617192-v"], "t_33_5": ["tough", "tough", "a", "02447344-a"], "t_33_7": ["papery", "papery", "a", "02414599-s"], "t_33_8": ["cocoon", "cocoon", "n", "02312744-n"], "t_33_10": ["pupates", "pupate", "v", "00096520-v"]}, "s_34": {"t_34_3": ["two_weeks", "two_weeks", "n", "15170331-n"], "t_34_6": ["first", "first", "a", "02202047-s"], "t_34_7": ["young", "young", "n", "01321579-n"], "t_34_8": ["emerge", "emerge", "v", "00423971-v"], "t_34_10": ["four", "four", "a", "02186665-s"], "t_34_12": ["eight", "eight", "a", "02187073-s"], "t_34_13": ["small", "small", "a", "01649031-s"], "t_34_14": ["daughters", "daughter", "n", "09992837-n"], "t_34_16": ["begin", "begin", "v", "00345761-v"], "t_34_18": ["play", "play", "v", "00013615-v"], "t_34_20": ["role", "role", "n", "00720565-n"], "t_34_22": ["worker_bees", "worker_bee", "n", "02207805-n"], "t_34_24": ["collecting", "collect", "v", "02304982-v"], "t_34_25": ["pollen", "pollen", "n", "11675537-n"], "t_34_27": ["nectar", "nectar", "n", "14846779-n"], "t_34_30": ["field", "field", "n", "08569998-n"], "t_34_32": ["caring", "care", "v", "02550296-v"], "t_34_35": ["new", "new", "a", "01640850-a"], "t_34_36": ["young", "young", "a", "01646941-a"], "t_34_37": ["generation", "generation", "n", "08368907-n"], "t_34_40": ["queen", "queen", "n", "02313008-n"], "t_34_41": ["retires", "retire", "v", "02428487-v"], "t_34_44": ["life", "life", "n", "13961399-n"], "t_34_46": ["egg_laying", "egg_laying", "n", "13506477-n"]}, "s_35": {"t_35_2": ["first", "first", "a", "02202047-s"], "t_35_3": ["worker_bees", "worker_bee", "n", "02207805-n"], "t_35_5": ["not", "not", "r", "00024073-r"], "t_35_6": ["mate", "mate", "v", "01428853-v"], "t_35_8": ["lay", "lay", "v", "01545079-v"], "t_35_9": ["eggs", "egg", "n", "01460457-n"], "t_35_11": ["males", "male", "n", "01321230-n"], "t_35_13": ["mating", "mating", "n", "00847340-n"], "t_35_14": ["females", "female", "n", "01320872-n"], "t_35_16": ["not", "not", "r", "00024073-r"], "t_35_17": ["emerge", "emerge", "v", "00423971-v"], "t_35_19": ["later", "later", "r", "00061203-r"], "t_35_22": ["season", "season", "n", "15236475-n"]}, "s_36": {"t_36_2": ["broods", "brood", "n", "07990824-n"], "t_36_4": ["workers", "worker", "n", "02207449-n"], "t_36_6": ["appear", "appear", "v", "00422090-v"], "t_36_7": ["later", "later", "r", "00061203-r"], "t_36_8": ["tend", "tend", "v", "02719399-v"], "t_36_10": ["be", "be", "v", "02604760-v"], "t_36_11": ["bigger", "bigger", "a", "01383756-s"], "t_36_14": ["first", "first", "a", "02202047-s"], "t_36_17": ["probably", "probably", "r", "00138611-r"], "t_36_21": ["better", "better", "r", "00059607-r"], "t_36_22": ["fed", "feed", "v", "01182021-v"]}, "s_37": {"t_37_3": ["middle", "middle", "a", "01014953-s"], "t_37_6": ["summer", "summer", "n", "15237250-n"], "t_37_10": ["larvae", "larva", "n", "02311060-n"], "t_37_11": ["apparently", "apparently", "r", "00039941-r"], "t_37_12": ["receive", "receive", "v", "02210119-v"], "t_37_13": ["such", "such", "r", "00147386-r"], "t_37_15": ["good", "good", "a", "01123148-a"], "t_37_16": ["diet", "diet", "n", "07561112-n"], "t_37_19": ["is", "be", "v", "02604760-v"], "t_37_21": ["optimal", "optimal", "a", "00228645-s"], "t_37_27": ["then", "then", "r", "00117903-r"], "t_37_29": ["young", "young", "a", "01646941-a"], "t_37_30": ["queens", "queen", "n", "02313008-n"], "t_37_31": ["begin", "begin", "v", "00345761-v"], "t_37_33": ["appear", "appear", "v", "00422090-v"]}, "s_38": {"t_38_1": ["Simultaneously", "simultaneously", "r", "00120095-r"], "t_38_3": ["males", "male", "n", "01321230-n"], "t_38_5": ["drones", "drone", "n", "02207179-n"], "t_38_7": ["produced", "produce", "v", "01752495-v"], "t_38_9": ["mostly", "mostly", "r", "00155621-r"], "t_38_12": ["unfertilized", "unfertilized", "a", "01002911-s"], "t_38_13": ["eggs", "egg", "n", "01460457-n"], "t_38_15": ["workers", "worker", "n", "02207449-n"], "t_38_19": ["few", "few", "n", "08388074-n"], "t_38_22": ["produced", "produce", "v", "01752495-v"], "t_38_25": ["queen", "queen", "n", "02313008-n"]}, "s_39": {"t_39_2": ["young", "young", "a", "01646941-a"], "t_39_3": ["queens", "queen", "n", "02313008-n"], "t_39_5": ["drones", "drone", "n", "02207179-n"], "t_39_6": ["leave", "leave", "v", "02009433-v"], "t_39_8": ["nest", "nest", "n", "09369169-n"], "t_39_10": ["mate", "mate", "v", "01428853-v"], "t_39_15": ["short", "short", "a", "01442186-a"], "t_39_16": ["period", "period", "n", "15113229-n"], "t_39_18": ["freedom", "freedom", "n", "13991823-n"], "t_39_21": ["fertilized", "fertilized", "v", "00502757-v"], "t_39_22": ["young", "young", "a", "01646941-a"], "t_39_23": ["queens", "queen", "n", "02313008-n"], "t_39_25": ["begin", "begin", "v", "00345761-v"], "t_39_27": ["dig", "dig", "v", "01309701-v"], "t_39_31": ["winter", "winter", "n", "15237782-n"]}, "s_40": {"t_40_2": ["is", "be", "v", "02604760-v"], "t_40_4": ["amazing", "amazing", "a", "02359789-s"], "t_40_5": ["fact", "fact", "n", "05817396-n"], "t_40_8": ["some", "some", "a", "02267308-a"], "t_40_9": ["species", "species", "n", "08110373-n"], "t_40_12": ["happen", "happen", "v", "00339934-v"], "t_40_15": ["summer", "summer", "n", "15237250-n"], "t_40_16": ["is", "be", "v", "02604760-v"], "t_40_17": ["still", "still", "r", "00031304-r"], "t_40_18": ["in_full_swing", "in_full_swing", "r", "00165445-r"], "t_40_20": ["for_instance", "for_instance", "r", "00159040-r"], "t_40_23": ["August", "august", "n", "15212455-n"]}, "s_41": {"t_41_2": ["temperature", "temperature", "n", "05011790-n"], "t_41_3": ["then", "then", "r", "00117903-r"], "t_41_4": ["is", "be", "v", "02604760-v"], "t_41_5": ["still", "still", "r", "00031304-r"], "t_41_6": ["very", "very", "r", "00031899-r"], "t_41_7": ["high", "high", "a", "01210854-a"]}, "s_42": {"t_42_3": ["old", "old", "a", "01638438-a"], "t_42_4": ["nest", "nest", "n", "09369169-n"], "t_42_7": ["queen", "queen", "n", "02313008-n"], "t_42_11": ["early", "early", "a", "00812952-a"], "t_42_12": ["fall", "fall", "n", "15236859-n"], "t_42_13": ["cease", "cease", "v", "02680814-v"], "t_42_15": ["lay", "lay", "v", "01545079-v"], "t_42_17": ["fertilized", "fertilized", "v", "00502757-v"], "t_42_18": ["eggs", "egg", "n", "01460457-n"], "t_42_21": ["produce", "produce", "v", "01752495-v"], "t_42_22": ["females", "female", "n", "01320872-n"]}, "s_43": {"t_43_3": ["result", "result", "n", "11410625-n"], "t_43_6": ["proportion", "proportion", "n", "13815742-n"], "t_43_8": ["males", "male", "n", "01321230-n"], "t_43_11": ["leave", "leave", "v", "02009433-v"], "t_43_13": ["nest", "nest", "n", "09369169-n"], "t_43_15": ["increases", "increase", "v", "00156601-v"], "t_43_18": ["eventually", "eventually", "r", "00048138-r"], "t_43_20": ["old", "old", "a", "01638438-a"], "t_43_21": ["colony", "colony", "n", "07995856-n"], "t_43_23": ["die_out", "die_out", "v", "00427683-v"], "t_43_24": ["completely", "completely", "r", "00157624-r"]}, "s_44": {"t_44_2": ["nest", "nest", "n", "09369169-n"], "t_44_6": ["structure", "structure", "n", "04341686-n"], "t_44_10": ["cases", "case", "n", "07308889-n"], "t_44_11": ["housed", "house", "v", "02459173-v"], "t_44_14": ["individuals", "individual", "n", "10203839-n"], "t_44_17": ["season", "season", "n", "15236475-n"], "t_44_18": ["was", "be", "v", "02655135-v"], "t_44_21": ["peak", "peak", "n", "15295045-n"], "t_44_24": ["now", "now", "r", "00049433-r"], "t_44_25": ["rapidly", "rapidly", "r", "00085811-r"], "t_44_26": ["destroyed", "destroy", "v", "01564144-v"], "t_44_29": ["scavenging", "scavenging", "v", "01534043-v"], "t_44_30": ["larvae", "larva", "n", "02311060-n"], "t_44_32": ["certain", "certain", "a", "00700884-s"], "t_44_33": ["beetles", "beetle", "n", "02164464-n"], "t_44_35": ["moths", "moth", "n", "02283201-n"]}, "s_45": {"t_45_1": ["Not", "not", "r", "00024073-r"], "t_45_2": ["always", "always", "r", "00019339-r"], "t_45_4": ["though", "though", "r", "00119139-r"], "t_45_8": ["development", "development", "n", "13489037-n"], "t_45_11": ["bumblebee", "bumblebee", "n", "02209624-n"], "t_45_12": ["colony", "colony", "n", "07995856-n"], "t_45_13": ["take_place", "take_place", "v", "00339934-v"], "t_45_16": ["smooth", "smooth", "a", "02236842-a"], "t_45_17": ["fashion", "fashion", "n", "00415226-n"], "t_45_20": ["just", "just", "r", "00033308-r"], "t_45_21": ["described", "describe", "v", "00965035-v"]}, "s_46": {"t_46_1": ["Some", "some", "a", "02267308-a"], "t_46_2": ["members", "member", "n", "13810615-n"], "t_46_5": ["bee", "bee", "n", "02206856-n"], "t_46_6": ["family", "family", "n", "08107499-n"], "t_46_8": ["become", "become", "v", "02626604-v"], "t_46_9": ["idlers", "idler", "n", "10197967-n"], "t_46_11": ["social", "social", "a", "02248349-a"], "t_46_12": ["parasites", "parasite", "n", "01384687-n"], "t_46_14": ["live", "live", "v", "02616713-v"], "t_46_17": ["expense", "expense", "n", "13275495-n"], "t_46_20": ["hardworking", "hardworking", "a", "00754682-s"], "t_46_21": ["relatives", "relative", "n", "01328302-n"]}, "s_47": {"t_47_1": ["Bumblebees", "bumblebee", "n", "02209624-n"], "t_47_3": ["thus", "thus", "r", "00121135-r"], "t_47_4": ["suffer", "suffer", "v", "00204750-v"], "t_47_5": ["severely", "severely", "r", "00015953-r"], "t_47_8": ["onslaughts", "onslaught", "n", "07306160-n"], "t_47_14": ["cuckoo_bumblebee", "cuckoo-bumblebee", "n", "02209964-n"], "t_47_19": ["called", "called", "v", "01028748-v"], "t_47_22": ["European_countries", "european_country", "n", "08696931-n"]}, "s_48": {"t_48_1": ["Female", "female", "n", "01320872-n"], "t_48_2": ["individuals", "individual", "n", "10203839-n"], "t_48_4": ["Psithyrus", "psithyrus", "n", "02209755-n"], "t_48_5": ["look", "look", "v", "00033599-v"], "t_48_6": ["deceptively", "deceptively", "r", "00082148-r"], "t_48_9": ["workers", "worker", "n", "02207449-n"], "t_48_11": ["queens", "queen", "n", "02313008-n"], "t_48_14": ["bumblebees", "bumblebee", "n", "02209624-n"], "t_48_16": ["victimize", "victimize", "v", "02574205-v"]}, "s_49": {"t_49_2": ["one", "one", "n", "13742573-n"], "t_49_3": ["sure", "sure", "a", "00724397-s"], "t_49_4": ["way", "way", "n", "00172710-n"], "t_49_6": ["tell", "tell_apart", "v", "02193194-v"], "t_49_7": ["victim", "victim", "n", "10752093-n"], "t_49_9": ["villain", "villain", "n", "10753546-n"], "t_49_11": ["is", "be", "v", "02616386-v"], "t_49_13": ["examine", "examine", "v", "02131279-v"], "t_49_15": ["hind_legs", "hind_leg", "n", "02464626-n"], "t_49_19": ["case", "case", "n", "13943400-n"], "t_49_22": ["idler", "idler", "n", "10197967-n"], "t_49_24": ["Psithyrus", "psithyrus", "n", "02209755-n"], "t_49_26": ["lack", "lack", "v", "02632353-v"], "t_49_28": ["pollen", "pollen", "n", "11675537-n"], "t_49_29": ["baskets", "basket", "n", "13765207-n"], "t_49_31": ["naturally", "naturally", "r", "00038625-r"]}, "s_50": {"t_50_2": ["female", "female", "a", "01477806-a"], "t_50_3": ["parasite", "parasite", "n", "01384687-n"], "t_50_4": ["spends", "spend", "v", "02708420-v"], "t_50_5": ["much", "much", "a", "01553629-a"], "t_50_6": ["time", "time", "n", "15270431-n"], "t_50_9": ["efforts", "effort", "n", "00786195-n"], "t_50_11": ["find", "find", "v", "02213336-v"], "t_50_13": ["nest", "nest", "n", "09369169-n"], "t_50_16": ["host", "host", "n", "01385527-n"]}, "s_51": {"t_51_3": ["succeeds", "succeed", "v", "02524171-v"], "t_51_6": ["usually", "usually", "r", "00106921-r"], "t_51_7": ["manages", "manage", "v", "02522864-v"], "t_51_9": ["slip_in", "slip_in", "v", "01025602-v"], "t_51_10": ["unobtrusively", "unobtrusively", "r", "00412987-r"], "t_51_13": ["deposit", "deposit", "v", "01575675-v"], "t_51_15": ["egg", "egg", "n", "01460457-n"], "t_51_18": ["completed", "completed", "a", "00521329-s"], "t_51_19": ["loaf", "loaf", "n", "07683786-n"], "t_51_21": ["beebread", "beebread", "n", "14774090-n"], "t_51_24": ["bumblebees", "bumblebee", "n", "02209624-n"], "t_51_25": ["seal", "seal", "v", "01353405-v"], "t_51_27": ["egg", "egg", "n", "01460457-n"], "t_51_28": ["compartment", "compartment", "n", "03080309-n"]}, "s_52": {"t_52_2": ["hosts", "host", "n", "01385527-n"], "t_52_3": ["never", "never", "r", "00020759-r"], "t_52_4": ["seem", "seem", "v", "02133435-v"], "t_52_6": ["recognize", "recognize", "v", "00728617-v"], "t_52_9": ["is", "be", "v", "02604760-v"], "t_52_10": ["amiss", "amiss", "a", "01092371-s"], "t_52_15": ["compartment", "compartment", "n", "03080309-n"], "t_52_16": ["afterward", "afterward", "r", "00061203-r"], "t_52_18": ["sealed", "seal", "v", "01353405-v"], "t_52_19": ["normally", "normally", "r", "00106921-r"]}, "s_53": {"t_53_1": ["Thus", "thus", "r", "00043003-r"], "t_53_4": ["larvae", "larva", "n", "02311060-n"], "t_53_7": ["intruder", "intruder", "n", "10213652-n"], "t_53_9": ["develop", "develop", "v", "00252019-v"], "t_53_12": ["expense", "expense", "n", "13275495-n"], "t_53_15": ["rightful", "rightful", "a", "01370475-s"], "t_53_16": ["inhabitants", "inhabitant", "n", "09620078-n"], "t_53_19": ["store", "store", "n", "13367070-n"], "t_53_21": ["beebread", "beebread", "n", "14774090-n"]}, "s_54": {"t_54_1": ["Later_on", "later_on", "r", "00061203-r"], "t_54_6": ["mother", "mother", "n", "10332385-n"], "t_54_7": ["Psithyrus", "psithyrus", "n", "02209755-n"], "t_54_9": ["fed", "feed", "v", "01182021-v"], "t_54_12": ["Bombus", "bombus", "n", "02209508-n"], "t_54_13": ["workers", "worker", "n", "02207449-n"]}, "s_55": {"t_55_1": ["Worse", "worse", "r", "00017077-r"], "t_55_2": ["still", "still", "r", "00017639-r"], "t_55_6": ["number", "number", "n", "05121418-n"], "t_55_8": ["cases", "case", "n", "13943400-n"], "t_55_11": ["been", "be", "v", "02604760-v"], "t_55_12": ["claimed", "claim", "v", "00758333-v"], "t_55_15": ["Psithyrus", "psithyrus", "n", "02209755-n"], "t_55_16": ["female", "female", "n", "01320872-n"], "t_55_17": ["kills_off", "kill_off", "v", "01327582-v"], "t_55_19": ["Bombus", "bombus", "n", "02209508-n"], "t_55_20": ["queen", "queen", "n", "02313008-n"]}, "s_56": {"t_56_2": ["let", "let", "v", "02423183-v"], "t_56_4": ["return", "return", "v", "00387310-v"], "t_56_8": ["gruesome", "gruesome", "a", "00195684-s"], "t_56_9": ["interlude", "interlude", "n", "15272685-n"], "t_56_13": ["willow", "willow", "n", "12724942-n"], "t_56_14": ["catkins", "catkin", "n", "11674798-n"], "t_56_17": ["spring", "spring", "n", "15237044-n"], "t_56_20": ["are", "be", "v", "02603699-v"], "t_56_21": ["other", "other", "a", "02069355-a"], "t_56_22": ["wild", "wild", "a", "02389220-a"], "t_56_23": ["bees", "bee", "n", "02206856-n"], "t_56_25": ["command", "command", "v", "01018177-v"], "t_56_27": ["attention", "attention", "n", "05702275-n"]}, "s_57": {"t_57_2": ["is", "be", "v", "02604760-v"], "t_57_3": ["almost", "almost", "r", "00073033-r"], "t_57_4": ["certain", "certain", "a", "00335421-a"], "t_57_10": ["usually", "usually", "r", "00106921-r"], "t_57_11": ["a_trifle", "a_trifle", "r", "00033663-r"], "t_57_12": ["smaller", "smaller", "a", "01394922-s"], "t_57_15": ["honeybees", "honeybee", "n", "02208280-n"], "t_57_17": ["are", "be", "v", "02616386-v"], "t_57_20": ["mining_bees", "mining_bee", "n", "02210427-n"]}, "s_58": {"t_58_2": ["are", "be", "v", "02603699-v"], "t_58_3": ["about", "about", "r", "00007015-r"], "t_58_5": ["different", "different", "a", "02064745-a"], "t_58_6": ["kinds", "kind", "n", "05839024-n"], "t_58_8": ["Andrena", "andrena", "n", "02210427-n"], "t_58_10": ["Europe", "europe", "n", "09275473-n"], "t_58_11": ["alone", "alone", "r", "00008600-r"]}, "s_59": {"t_59_4": ["favorites", "favorite", "n", "05790758-n"], "t_59_5": ["is", "be", "v", "02616386-v"], "t_59_9": ["species", "species", "n", "08110373-n"], "t_59_10": ["very", "very", "r", "00510749-r"], "t_59_11": ["common", "common", "a", "00485711-a"], "t_59_13": ["England", "england", "n", "08871007-n"], "t_59_18": ["sometimes", "sometimes", "r", "00021878-r"], "t_59_19": ["referred", "refer", "v", "00655555-v"], "t_59_23": ["lawn", "lawn", "n", "08591592-n"], "t_59_24": ["bee", "bee", "n", "02206856-n"]}, "s_60": {"t_60_2": ["females", "female", "n", "01320872-n"], "t_60_3": ["like", "like", "v", "01777210-v"], "t_60_5": ["burrow", "burrow", "v", "02042067-v"], "t_60_8": ["short", "short", "a", "02386612-a"], "t_60_9": ["turf", "turf", "n", "09463919-n"], "t_60_11": ["well-kept", "well-kept", "a", "00737515-s"], "t_60_12": ["lawns", "lawn", "n", "08591592-n"], "t_60_16": ["little", "little", "a", "01391351-a"], "t_60_17": ["mounds", "mound", "n", "07961480-n"], "t_60_19": ["earth", "earth", "n", "14842992-n"], "t_60_20": ["often", "often", "r", "00035058-r"], "t_60_21": ["appear", "appear", "v", "00422090-v"], "t_60_24": ["hundreds", "hundred", "n", "13750415-n"]}, "s_61": {"t_61_1": ["Almost", "almost", "r", "00073033-r"], "t_61_2": ["equal", "equal", "a", "00889831-a"], "t_61_4": ["size", "size", "n", "05098942-n"], "t_61_7": ["honeybee", "honeybee", "n", "02208280-n"]}, "s_62": {"t_62_2": ["is", "be", "v", "02604760-v"], "t_62_3": ["much", "much", "r", "00059086-r"], "t_62_4": ["more", "more", "r", "00099341-r"], "t_62_5": ["beautiful", "beautiful", "a", "00217728-a"], "t_62_7": ["color", "color", "n", "04956594-n"], "t_62_9": ["at_least", "at_least", "r", "00104661-r"], "t_62_12": ["female", "female", "n", "01320872-n"], "t_62_15": ["species", "species", "n", "08110373-n"], "t_62_18": ["rich", "rich", "a", "00403385-s"], "t_62_20": ["velvety", "velvety", "a", "02238310-s"], "t_62_22": ["rusty", "rusty", "a", "00382874-s"], "t_62_23": ["red", "red", "a", "00381097-s"]}, "s_63": {"t_63_2": ["males", "male", "n", "01321230-n"], "t_63_3": ["are", "be", "v", "02604760-v"], "t_63_4": ["much", "much", "r", "00059086-r"], "t_63_5": ["duller", "dull", "a", "00393992-s"]}, "s_64": {"t_64_3": ["mated", "mate", "v", "01428853-v"], "t_64_6": ["Andrena", "andrena", "n", "02210427-n"], "t_64_7": ["female", "female", "n", "01320872-n"], "t_64_8": ["digs", "dig", "v", "01311103-v"], "t_64_10": ["hole", "hole", "n", "09304465-n"], "t_64_11": ["straight", "straight", "r", "00058128-r"], "t_64_12": ["down", "down", "r", "00095320-r"], "t_64_15": ["ground", "ground", "n", "09334396-n"], "t_64_17": ["forming", "form", "v", "01659248-v"], "t_64_19": ["burrow", "burrow", "n", "09230041-n"], "t_64_22": ["size", "size", "n", "05098942-n"], "t_64_25": ["lead_pencil", "lead_pencil", "n", "03652100-n"]}, "s_65": {"t_65_2": ["bottom", "bottom", "n", "08511241-n"], "t_65_3": ["part", "part", "n", "09385911-n"], "t_65_6": ["burrow", "burrow", "n", "09230041-n"], "t_65_7": ["has", "have", "v", "02630189-v"], "t_65_9": ["number", "number", "n", "05121418-n"], "t_65_11": ["side", "side", "n", "08649345-n"], "t_65_12": ["tunnels", "tunnel", "n", "04497962-n"], "t_65_15": ["cells", "cell", "n", "02991711-n"], "t_65_22": ["provided", "provide", "v", "02327200-v"], "t_65_25": ["egg", "egg", "n", "01460457-n"], "t_65_28": ["store", "store", "n", "13367070-n"], "t_65_30": ["beebread", "beebread", "n", "14774090-n"]}, "s_66": {"t_66_2": ["development", "development", "n", "13489037-n"], "t_66_5": ["Andrena", "andrena", "n", "02210427-n"], "t_66_6": ["larvae", "larva", "n", "02311060-n"], "t_66_7": ["is", "be", "v", "02604760-v"], "t_66_8": ["very", "very", "r", "00031899-r"], "t_66_9": ["rapid", "rapid", "a", "00979697-s"], "t_66_15": ["end", "end", "n", "15266911-n"], "t_66_17": ["spring", "spring", "n", "15237044-n"], "t_66_20": ["already", "already", "r", "00031798-r"], "t_66_21": ["pupated", "pupate", "v", "00096520-v"], "t_66_23": ["become", "become", "v", "02626604-v"], "t_66_24": ["adults", "adult", "n", "01321456-n"]}, "s_67": {"t_67_4": ["still", "still", "r", "00031304-r"], "t_67_5": ["enclosed", "enclose", "v", "02711114-v"], "t_67_8": ["larval", "larval", "a", "01490603-s"], "t_67_9": ["cells", "cell", "n", "02991711-n"], "t_67_11": ["remain", "remain", "v", "02727462-v"], "t_67_12": ["there", "there", "r", "00109151-r"], "t_67_15": ["summer", "summer", "n", "15237250-n"], "t_67_17": ["fall", "fall", "n", "15236859-n"], "t_67_20": ["winter", "winter", "n", "15237782-n"]}, "s_68": {"t_68_2": ["appearance", "appearance", "n", "07321772-n"], "t_68_4": ["next", "next", "a", "00127948-s"], "t_68_5": ["spring", "spring", "n", "15237044-n"], "t_68_7": ["coincides", "coincide", "v", "02660442-v"], "t_68_10": ["almost", "almost", "r", "00073033-r"], "t_68_11": ["uncanny", "uncanny", "a", "01575424-s"], "t_68_12": ["way", "way", "n", "04928903-n"], "t_68_15": ["flowering", "flowering", "n", "13439570-n"], "t_68_18": ["host", "host", "n", "01385527-n"], "t_68_19": ["plants", "plant", "n", "00017222-n"]}, "s_69": {"t_69_3": ["Sacramento", "sacramento", "n", "09064966-n"], "t_69_4": ["valley", "valley", "n", "09468604-n"], "t_69_6": ["California", "california", "n", "09060768-n"], "t_69_8": ["for_instance", "for_instance", "r", "00159040-r"], "t_69_12": ["been", "be", "v", "02604760-v"], "t_69_13": ["observed", "observe", "v", "02154508-v"], "t_69_16": ["was", "be", "v", "02749904-v"], "t_69_17": ["not", "not", "r", "00024073-r"], "t_69_18": ["one", "one", "a", "02186338-s"], "t_69_19": ["day", "day", "n", "15155220-n"], "t_69_21": ["difference", "difference", "n", "04748836-n"], "t_69_24": ["emergence", "emergence", "n", "07319909-n"], "t_69_30": ["opening", "opening", "n", "00383390-n"], "t_69_33": ["willow", "willow", "n", "12724942-n"], "t_69_34": ["catkins", "catkin", "n", "11674798-n"]}, "s_70": {"t_70_3": ["be_due", "be_due", "v", "02634567-v"], "t_70_6": ["completely", "completely", "r", "00008007-r"], "t_70_7": ["identical", "identical", "a", "02068946-s"], "t_70_8": ["response", "response", "n", "00859001-n"], "t_70_11": ["weather", "weather", "n", "11524662-n"], "t_70_15": ["plant", "plant", "n", "00017222-n"], "t_70_18": ["animal", "animal", "n", "00015388-n"]}, "s_71": {"t_71_3": ["male", "male", "a", "01476685-a"], "t_71_5": ["female", "female", "a", "01477806-a"], "t_71_8": ["mated", "mate", "v", "01428853-v"], "t_71_11": ["cycle", "cycle", "n", "15287830-n"], "t_71_13": ["repeated", "repeat", "v", "01734502-v"]}, "s_72": {"t_72_2": ["Andrena", "andrena", "n", "02210427-n"], "t_72_3": ["is", "be", "v", "02604760-v"], "t_72_4": ["gregarious", "gregarious", "a", "02252634-a"], "t_72_6": ["so", "so", "r", "00118363-r"], "t_72_10": ["find", "find", "v", "02128873-v"], "t_72_11": ["hundreds", "hundred", "n", "13750415-n"], "t_72_13": ["hundreds", "hundred", "n", "13750415-n"], "t_72_15": ["burrows", "burrow", "n", "09230041-n"], "t_72_16": ["together", "together", "r", "00116994-r"], "t_72_20": ["still", "still", "r", "00031304-r"], "t_72_21": ["call", "call", "v", "00971015-v"], "t_72_24": ["solitary", "solitary", "a", "02253205-s"], "t_72_25": ["bee", "bee", "n", "02206856-n"]}, "s_73": {"t_73_2": ["life_history", "life_history", "n", "06515827-n"], "t_73_3": ["is", "be", "v", "02604760-v"], "t_73_4": ["much", "much", "r", "00059086-r"], "t_73_5": ["simpler", "simple", "a", "02174896-a"], "t_73_10": ["truly", "truly", "r", "00037226-r"], "t_73_11": ["colonial", "colonial", "a", "02700029-a"], "t_73_12": ["bumblebees", "bumblebee", "n", "02209624-n"], "t_73_15": ["serve", "serve", "v", "02670890-v"], "t_73_18": ["example", "example", "n", "05937112-n"], "t_73_21": ["life_cycle", "life_cycle", "n", "11473807-n"], "t_73_23": ["many", "many", "a", "01551633-a"], "t_73_24": ["other", "other", "a", "02069355-a"], "t_73_25": ["species", "species", "n", "08110373-n"]}, "s_74": {"t_74_1": ["After_all", "after_all", "r", "00151149-r"], "t_74_3": ["social", "social", "a", "02248349-a"], "t_74_4": ["life", "life", "n", "13963192-n"], "t_74_7": ["group", "group", "n", "00031264-n"], "t_74_10": ["bees", "bee", "n", "02206856-n"], "t_74_11": ["is", "be", "v", "02604760-v"], "t_74_12": ["by_no_means", "by_no_means", "r", "00057042-r"], "t_74_13": ["general", "general", "a", "01101391-a"], "t_74_17": ["certainly", "certainly", "r", "00144722-r"], "t_74_18": ["is", "be", "v", "02604760-v"], "t_74_20": ["striking", "striking", "a", "01284212-s"], "t_74_21": ["feature", "feature", "n", "05849789-n"]}, "s_75": {"t_75_3": ["basis", "basis", "n", "05793554-n"], "t_75_6": ["life_history", "life_history", "n", "06515827-n"], "t_75_9": ["like", "like", "v", "01824736-v"], "t_75_11": ["think", "think", "v", "00631737-v"], "t_75_13": ["Andrena", "andrena", "n", "02210427-n"], "t_75_14": ["is", "be", "v", "02604760-v"], "t_75_15": ["more", "more", "r", "00099341-r"], "t_75_16": ["primitive", "primitive", "a", "00817731-s"], "t_75_19": ["bumblebees", "bumblebee", "n", "02209624-n"]}, "s_76": {"t_76_2": ["way", "way", "n", "04928903-n"], "t_76_6": ["transports", "transport", "v", "01449974-v"], "t_76_8": ["pollen", "pollen", "n", "11675537-n"], "t_76_9": ["is", "be", "v", "02604760-v"], "t_76_10": ["not", "not", "r", "00024073-r"], "t_76_11": ["so", "so", "r", "00146594-r"], "t_76_12": ["perfect", "perfect", "a", "01749320-a"], "t_76_14": ["either", "either", "r", "00024893-r"]}, "s_77": {"t_77_2": ["lacks", "lack", "v", "02632353-v"], "t_77_3": ["pollen", "pollen", "n", "11675537-n"], "t_77_4": ["baskets", "basket", "n", "13765207-n"], "t_77_6": ["possesses", "possess", "v", "02632167-v"], "t_77_7": ["only", "only", "r", "00004722-r"], "t_77_9": ["large_number", "large_number", "n", "13775093-n"], "t_77_11": ["long", "long", "a", "01433493-a"], "t_77_13": ["branched", "branched", "a", "02479602-s"], "t_77_14": ["hairs", "hair", "n", "05254795-n"], "t_77_17": ["legs", "leg", "n", "05561507-n"], "t_77_22": ["pollen", "pollen", "n", "11675537-n"], "t_77_23": ["grains", "grain", "n", "09290777-n"], "t_77_25": ["collect", "collect", "v", "02304982-v"]}, "s_78": {"t_78_1": ["Still", "still", "r", "00027384-r"], "t_78_2": ["Andrena", "andrena", "n", "02210427-n"], "t_78_4": ["do", "do", "v", "02560585-v"], "t_78_6": ["reasonably", "reasonably", "r", "00035718-r"], "t_78_7": ["good", "good", "a", "01123148-a"], "t_78_8": ["job", "job", "n", "00719705-n"], "t_78_10": ["so", "so", "r", "00118363-r"], "t_78_13": ["animal", "animal", "n", "00015388-n"], "t_78_16": ["full", "full", "a", "01083157-a"], "t_78_17": ["pollen", "pollen", "n", "11675537-n"], "t_78_18": ["load", "load", "n", "03679986-n"], "t_78_19": ["looks_like", "look_like", "v", "02665617-v"], "t_78_21": ["gay", "gay", "a", "00407151-s"], "t_78_22": ["little", "little", "a", "01391351-a"], "t_78_23": ["piece", "piece", "n", "09385911-n"], "t_78_25": ["yellow", "yellow", "n", "04965661-n"], "t_78_26": ["down", "down", "n", "01896561-n"], "t_78_27": ["floating", "float", "v", "01902783-v"], "t_78_30": ["wind", "wind", "n", "11525955-n"]}, "s_79": {"t_79_1": ["Closely", "closely", "r", "00160440-r"], "t_79_2": ["related", "related", "a", "01971237-a"], "t_79_5": ["andrenas", "andrena", "n", "02210427-n"], "t_79_6": ["are", "be", "v", "02604760-v"], "t_79_8": ["nomias", "nomia", "n", "02210567-n"], "t_79_10": ["alkali_bees", "alkali_bee", "n", "02210921-n"]}, "s_80": {"t_80_1": ["Nomia_melanderi", "nomia_melanderi", "n", "02210921-n"], "t_80_4": ["found", "find", "v", "02154508-v"], "t_80_6": ["tremendous", "tremendous", "a", "01385255-s"], "t_80_7": ["numbers", "number", "n", "13582013-n"], "t_80_9": ["certain", "certain", "a", "00700884-s"], "t_80_10": ["parts", "part", "n", "08630039-n"], "t_80_13": ["United_States", "united_states", "n", "09044862-n"], "t_80_14": ["west", "west", "n", "13834399-n"], "t_80_17": ["Great_Plains", "location", "n", "00027167-n"], "t_80_19": ["for_example", "for_example", "r", "00159040-r"], "t_80_22": ["Utah", "utah", "n", "09147046-n"], "t_80_24": ["central", "central", "n", "02994858-n"], "t_80_25": ["Washington", "washington", "n", "09152944-n"]}, "s_81": {"t_81_3": ["United_States", "united_states", "n", "09044862-n"], "t_81_4": ["Department_of_Agriculture", "department_of_agriculture", "n", "08128964-n"], "t_81_12": ["devoted", "devote", "v", "00887463-v"], "t_81_13": ["entirely", "entirely", "r", "00008007-r"], "t_81_15": ["insects", "insect", "n", "02159955-n"], "t_81_17": ["George_E._Bohart", "person", "n", "00007846-n"], "t_81_18": ["mentions", "mention", "v", "01024190-v"], "t_81_20": ["site", "site", "n", "08622950-n"], "t_81_22": ["Utah", "utah", "n", "09147046-n"], "t_81_25": ["estimated", "estimate", "v", "00672433-v"], "t_81_27": ["contain", "contain", "v", "02629535-v"], "t_81_29": ["nesting", "nest", "v", "02654947-v"], "t_81_30": ["females", "female", "n", "01320872-n"]}, "s_82": {"t_82_1": ["Often", "often", "r", "00035058-r"], "t_82_3": ["burrows", "burrow", "n", "09230041-n"], "t_82_4": ["are", "be", "v", "02655135-v"], "t_82_5": ["only", "only", "r", "00004722-r"], "t_82_7": ["inch", "inch", "n", "13649791-n"], "t_82_9": ["two", "two", "a", "02186470-s"], "t_82_10": ["apart", "apart", "r", "00181075-r"], "t_82_14": ["bee", "bee", "n", "02206856-n"], "t_82_15": ["cities", "city", "n", "08524735-n"], "t_82_16": ["cover", "cover", "v", "02687916-v"], "t_82_17": ["several", "several", "a", "02268268-s"], "t_82_18": ["acres", "acres", "n", "13246662-n"]}, "s_83": {"t_83_2": ["life_history", "life_history", "n", "06515827-n"], "t_83_5": ["alkali_bee", "alkali_bee", "n", "02210921-n"], "t_83_6": ["is", "be", "v", "02604760-v"], "t_83_7": ["similar", "similar", "a", "02071420-a"], "t_83_11": ["Andrena", "andrena", "n", "02210427-n"], "t_83_15": ["first", "first", "a", "02202047-s"], "t_83_16": ["activity", "activity", "n", "14006945-n"], "t_83_19": ["adults", "adult", "n", "01321456-n"], "t_83_21": ["not", "not", "r", "00024073-r"], "t_83_22": ["take_place", "take_place", "v", "00339934-v"], "t_83_24": ["summer", "summer", "n", "15237250-n"], "t_83_28": ["individuals", "individual", "n", "10203839-n"], "t_83_29": ["hibernate", "hibernate", "v", "00015946-v"], "t_83_32": ["prepupal", "prepupal", "a", "01491067-s"], "t_83_33": ["stage", "stage", "n", "13939892-n"]}, "s_84": {"t_84_2": ["most", "most", "a", "01557120-a"], "t_84_3": ["places", "place", "n", "08642037-n"], "t_84_6": ["are", "be", "v", "02749904-v"], "t_84_7": ["two", "two", "a", "02186470-s"], "t_84_8": ["generations", "generation", "n", "08368907-n"], "t_84_10": ["year", "year", "n", "15203791-n"], "t_84_13": ["second", "second", "a", "02202146-s"], "t_84_14": ["brood", "brood", "n", "07990824-n"], "t_84_16": ["adults", "adult", "n", "01321456-n"], "t_84_17": ["appearing", "appear", "v", "00422090-v"], "t_84_18": ["late", "late", "a", "00816481-a"], "t_84_21": ["summer", "summer", "n", "15237250-n"]}, "s_85": {"t_85_3": ["plead", "plead", "v", "00760576-v"], "t_85_4": ["guilty", "guilty", "a", "01320988-a"], "t_85_7": ["special", "special", "a", "01104026-s"], "t_85_8": ["sympathy", "sympathy", "n", "06199142-n"], "t_85_10": ["nomias", "nomia", "n", "02210567-n"]}, "s_86": {"t_86_3": ["just", "just", "r", "00004722-r"], "t_86_4": ["be", "be", "v", "02616386-v"], "t_86_5": ["pride", "pride", "n", "07508486-n"], "t_86_8": ["adopted", "adopted", "a", "01034296-a"], "t_86_9": ["State_of_Washington", "location", "n", "00027167-n"], "t_86_12": ["certainly", "certainly", "r", "00144722-r"], "t_86_14": ["love", "love", "v", "01828736-v"], "t_86_16": ["visit", "visit", "v", "01843689-v"], "t_86_18": ["mound", "mound", "n", "09326662-n"], "t_86_19": ["cities", "city", "n", "08524735-n"], "t_86_21": ["Yakima", "location", "n", "00027167-n"], "t_86_23": ["Prosser", "location", "n", "00027167-n"], "t_86_25": ["July", "july", "n", "15212167-n"], "t_86_27": ["August", "august", "n", "15212455-n"], "t_86_31": ["bees", "bee", "n", "02206856-n"], "t_86_32": ["are", "be", "v", "02604760-v"], "t_86_35": ["most", "most", "a", "01555732-a"], "t_86_36": ["active", "active", "a", "00031974-a"], "t_86_37": ["period", "period", "n", "15113229-n"]}, "s_87": {"t_87_2": ["name", "name", "n", "06333653-n"], "t_87_4": ["alkali_bee", "alkali_bee", "n", "02210921-n"], "t_87_6": ["indicates", "indicate", "v", "00928015-v"], "t_87_10": ["look_for", "look_for", "v", "01315613-v"], "t_87_13": ["rather", "rather", "r", "00018302-r"], "t_87_14": ["inhospitable", "inhospitable", "a", "01242489-a"], "t_87_15": ["places", "place", "n", "08664443-n"]}, "s_88": {"t_88_1": ["Sometimes", "sometimes", "r", "00021878-r"], "t_88_4": ["by_no_means", "by_no_means", "r", "00057042-r"], "t_88_5": ["always", "always", "r", "00019339-r"], "t_88_8": ["are", "be", "v", "02604760-v"], "t_88_9": ["indeed", "indeed", "r", "00037641-r"], "t_88_10": ["alkaline", "alkaline", "a", "00025728-a"]}, "s_89": {"t_89_2": ["thing", "thing", "n", "13943968-n"], "t_89_3": ["is", "be", "v", "02616386-v"], "t_89_6": ["bees", "bee", "n", "02206856-n"], "t_89_7": ["love", "love", "v", "01828736-v"], "t_89_9": ["fine-grained", "fine-grained", "a", "02233390-s"], "t_89_10": ["soil", "soil", "n", "14844693-n"], "t_89_12": ["is", "be", "v", "02604760-v"], "t_89_13": ["moist", "moist", "a", "02548820-s"], "t_89_17": ["water", "water", "n", "14845743-n"], "t_89_20": ["ground", "ground", "n", "09334396-n"], "t_89_22": ["not", "not", "r", "00024073-r"], "t_89_23": ["be", "be", "v", "02604760-v"], "t_89_24": ["stagnant", "stagnant", "a", "01241248-s"], "t_89_25": ["either", "either", "r", "00024893-r"]}, "s_90": {"t_90_2": ["dislike", "dislike", "v", "01776727-v"], "t_90_3": ["dense", "dense", "a", "02416390-s"], "t_90_4": ["vegetation", "vegetation", "n", "08436759-n"]}, "s_91": {"t_91_4": ["find", "find", "v", "02248465-v"], "t_91_5": ["such", "such", "a", "01554230-s"], "t_91_6": ["conditions", "condition", "n", "13920835-n"]}, "s_92": {"t_92_2": ["best", "best", "a", "00227507-a"], "t_92_3": ["chance", "chance", "n", "14483917-n"], "t_92_5": ["of_course", "of_course", "r", "00038625-r"], "t_92_8": ["offered", "offer", "v", "02296726-v"], "t_92_10": ["gently", "gently", "r", "00181576-r"], "t_92_11": ["sloping", "sloping", "a", "01234747-s"], "t_92_12": ["terrain", "terrain", "n", "08674563-n"], "t_92_15": ["water", "water", "n", "14845743-n"], "t_92_16": ["remains", "remain", "v", "00117985-v"], "t_92_17": ["close", "close", "a", "00446921-a"], "t_92_20": ["surface", "surface", "n", "09451517-n"], "t_92_24": ["air", "air", "n", "14841267-n"], "t_92_25": ["is", "be", "v", "02604760-v"], "t_92_26": ["dry", "dry", "a", "02551380-a"], "t_92_28": ["so", "so", "r", "00118363-r"], "t_92_31": ["high", "high", "a", "01210854-a"], "t_92_32": ["evaporation", "evaporation", "n", "13572436-n"], "t_92_33": ["leaves", "leave", "v", "00360092-v"], "t_92_34": ["salty", "salty", "a", "02306874-s"], "t_92_35": ["deposits", "deposit", "n", "09428967-n"], "t_92_37": ["permit", "permit", "v", "02423183-v"], "t_92_38": ["only", "only", "r", "00008600-r"], "t_92_39": ["sparse", "sparse", "a", "00542359-s"], "t_92_40": ["plant", "plant", "n", "00017222-n"], "t_92_41": ["growth", "growth", "n", "08438067-n"]}}